{"title":"Prépublications","markdown":{"headingText":"Prépublications","headingAttr":{"id":"sec-prepublication","classes":[],"keyvalue":[]},"containsRefs":false,"markdown":"\n-   Pour diffuser rapidement et efficacement une version préliminaire mais avancée de ses travaux.\n\n    -   Permet des rétroactions rapides, internationales et nombreuses <https://scholarlykitchen.sspnet.org/2022/02/28/guest-post-preprint-feedback-is-here-lets-make-it-constructive-and-fast/>.\n\n    -   Cela permet de penser un article scientifique comme une continuité de version (*record of versions*), plutôt que comme une version stable ou figée (*version of record*). Comme pour un livre qui nécessite plusieurs éditions, d'additions et de corrections.\n\n    -   Certaines revues nommées épirevues (*overlay journal* <https://arxiv.org/abs/2204.03383> ou <https://fr.wikipedia.org/wiki/%C3%89pirevue>) créent des liens vers un document existant dans un dépôt de preprint, elles ajoutent une couche de révision par les pairs et de métadonnées.\n\n    -   L'existence croissante de dépôts régionaux et nationaux (ex: AfricArxiv ou SciELO) contribuent à la bibliodiversité linguistique et thématique dans l'esprit de l'Initiative de Helsinski.\n\n-   C'est une pratique qui date d'avant internet : les chercheurs s'envoyaient les documents par la poste pour contourner la lenteur des canaux de diffusion classiques.\n\n    -   C'était couteux (photocopies, timbres, secrétariats En 1978, Donald Knuth a inventé le langage LaTeX (utilisé pour ce manuel) et a permis de réduire les coûts de formatage des documents.) et limités à certains domaines de recherche spécifiques et bien financés (astrophysique, physique des particules, etc.). D'autres domaines comme l'économie faisait circuler des *working papers*.\n\n    -   Internet a accéléré la pratique et le dépôt de prépublications (qui a débuté avec la plateforme arXiv).\n\n    -   La recherche sur le Covid-19 a encore accéléré cette pratique de dépôt.\n\n    -   Il existe désormais un grand nombre de dépôts de prépublications pour tous les domaines (mathématiques, médecine, sciences sociales, etc.).\n\n-   Déposer son projet de recherche sous la forme d'une *pre-registration* (expliquer ses hypothèses et ses méthodes avant d'entreprendre la recherche) peut rendre la recherche plus robuste et plus fiable.\n\n-   Bien discuter de la pertinence de le faire avec sa directrice ou son directeur de recherche.\n\n    -   Comme le titre et les auteurs sont explicites, cela peut contrenir à certaines révisions par les pairs qui demandent une révision en double aveugle stricte.\n\n    -   Comme c'est une première diffusion, cela peut contrevenir à certaines revues qui demandent une soumission originale stricte.\n\n    -   Certains domaines comme la fabrication de bombes nucléaires, de bio-pathogènes ou de cryptographies se prêtent mal à ce type de diffusion <https://www.wired.com/story/making-science-more-open-good-research-bad-security/>.\n\n-   Ne pas soummettre de brouillons : il semble être recommandé de diffuser une version préliminaire mais proche de la version finale <https://twitter.com/tdietterich/status/1454968577358925824>. Exemple : une version incorporant les réponses au premier tour de révision si la revue donne son accord.\n\n## Dépôts de prépublication (*preprint*)\n\n-   Pourquoi ?\n\n    -   Obtenir des **commentaires** : comme pour une présentation dans une conférence ou un colloque.\n\n    -   **Partager** les travaux en temps réel avec votre équipe de recherche.\n\n    -   Donner accès à une **version préliminaire** soumise à une revue et **acceptée** par les éditeurs mais encore en cours de révision.\n\n    -   Obtenir une **date de priorité** : signaler que telle recherche a été déposée en exclusivité par tels chercheurs à telle date.\n\n    -   Augmenter la **visibilité**, etc.\n\n-   Quelques plateformes :\n\n    -   [OSF](https://osf.io/) : Open Science Framework\n\n    -   [Zenodo](https://zenodo.org/)\n","srcMarkdownNoYaml":""},"formats":{"html":{"identifier":{"display-name":"HTML","target-format":"html","base-format":"html"},"execute":{"fig-width":7,"fig-height":5,"fig-format":"retina","fig-dpi":96,"df-print":"default","error":false,"eval":true,"cache":null,"freeze":false,"echo":true,"output":true,"warning":true,"include":true,"keep-md":false,"keep-ipynb":false,"ipynb":null,"enabled":null,"daemon":null,"daemon-restart":false,"debug":false,"ipynb-filters":[],"ipynb-shell-interactivity":null,"plotly-connected":true,"engine":"markdown"},"render":{"keep-tex":false,"keep-typ":false,"keep-source":false,"keep-hidden":false,"prefer-html":false,"output-divs":true,"output-ext":"html","fig-align":"default","fig-pos":null,"fig-env":null,"code-fold":"none","code-overflow":"scroll","code-link":false,"code-line-numbers":false,"code-tools":false,"tbl-colwidths":"auto","merge-includes":true,"inline-includes":false,"preserve-yaml":false,"latex-auto-mk":true,"latex-auto-install":true,"latex-clean":true,"latex-min-runs":1,"latex-max-runs":10,"latex-makeindex":"makeindex","latex-makeindex-opts":[],"latex-tlmgr-opts":[],"latex-input-paths":[],"latex-output-dir":null,"link-external-icon":false,"link-external-newwindow":false,"self-contained-math":false,"format-resources":[],"notebook-links":true},"pandoc":{"standalone":true,"wrap":"none","default-image-extension":"png","to":"html","output-file":"prepublication.html"},"language":{"toc-title-document":"Table des matières","toc-title-website":"Sur cette page","related-formats-title":"Autres formats","related-notebooks-title":"Notebooks","source-notebooks-prefix":"La source","other-links-title":"Autres liens","code-links-title":"Liens de code","launch-dev-container-title":"Lancer le Dev Container","launch-binder-title":"Lancer le Binder","article-notebook-label":"Cahier d'articles","notebook-preview-download":"Télécharger le cahier","notebook-preview-download-src":"Télécharger le code source","notebook-preview-back":"Retour à l'article","manuscript-meca-bundle":"Archive MECA","section-title-abstract":"Résumé","section-title-appendices":"Annexes","section-title-footnotes":"Notes de bas de page","section-title-references":"Les références","section-title-reuse":"Réutilisation","section-title-copyright":"Droits d'auteur","section-title-citation":"Citation","appendix-attribution-cite-as":"Veuillez citer ce travail comme suit :","appendix-attribution-bibtex":"BibTeX","appendix-view-license":"Voir la Licence","title-block-author-single":"Auteur·rice","title-block-author-plural":"Auteur·rice·s","title-block-affiliation-single":"Affiliation","title-block-affiliation-plural":"Affiliations","title-block-published":"Date de publication","title-block-modified":"Modifié","title-block-keywords":"Mots clés","callout-tip-title":"Astuce","callout-note-title":"Note","callout-warning-title":"Avertissement","callout-important-title":"Important","callout-caution-title":"Mise en garde","code-summary":"Code","code-tools-menu-caption":"Code","code-tools-show-all-code":"Montrer tout le code","code-tools-hide-all-code":"Cacher tout le code","code-tools-view-source":"Voir les sources","code-tools-source-code":"Code source","tools-share":"Share","tools-download":"Download","code-line":"Ligne","code-lines":"Lignes","copy-button-tooltip":"Copier vers le presse-papier","copy-button-tooltip-success":"Copié","repo-action-links-edit":"Modifier cette page","repo-action-links-source":"Voir la source","repo-action-links-issue":"Faire part d'un problème","back-to-top":"Retour au sommet","search-no-results-text":"Pas de résultats","search-matching-documents-text":"documents trouvés","search-copy-link-title":"Copier le lien vers la recherche","search-hide-matches-text":"Cacher les correspondances additionnelles","search-more-match-text":"correspondance de plus dans ce document","search-more-matches-text":"correspondances de plus dans ce document","search-clear-button-title":"Effacer","search-text-placeholder":"","search-detached-cancel-button-title":"Annuler","search-submit-button-title":"Envoyer","search-label":"Recherche","toggle-section":"Basculer la section","toggle-sidebar":"Basculer la barre latérale","toggle-dark-mode":"Basculer le mode sombre","toggle-reader-mode":"Basculer en mode lecteur","toggle-navigation":"Basculer la navigation","crossref-fig-title":"Figure","crossref-tbl-title":"Table","crossref-lst-title":"Listing","crossref-thm-title":"Théorème","crossref-lem-title":"Lemme","crossref-cor-title":"Corollaire","crossref-prp-title":"Proposition","crossref-cnj-title":"Conjecture","crossref-def-title":"Définition","crossref-exm-title":"Exemple","crossref-exr-title":"Exercice","crossref-ch-prefix":"Chapitre","crossref-apx-prefix":"Annexe","crossref-sec-prefix":"Section","crossref-eq-prefix":"Équation","crossref-lof-title":"Liste des Figures","crossref-lot-title":"Liste des Tables","crossref-lol-title":"Liste des Listings","environment-proof-title":"Preuve","environment-remark-title":"Remarque","environment-solution-title":"Solution","listing-page-order-by":"Trier par","listing-page-order-by-default":"Ordre par défaut","listing-page-order-by-date-asc":"Le plus ancien","listing-page-order-by-date-desc":"Le plus récent","listing-page-order-by-number-desc":"Descendant","listing-page-order-by-number-asc":"Ascendant","listing-page-field-date":"Date","listing-page-field-title":"Titre","listing-page-field-description":"Description","listing-page-field-author":"Auteur·rice","listing-page-field-filename":"Nom de fichier","listing-page-field-filemodified":"Modifié","listing-page-field-subtitle":"Sous-titre","listing-page-field-readingtime":"Temps de lecture","listing-page-field-wordcount":"Compteur de Mots","listing-page-field-categories":"Catégories","listing-page-minutes-compact":"{0} min.","listing-page-category-all":"Tous","listing-page-no-matches":"Aucun article correspondant","listing-page-words":"{0} mots","listing-page-filter":"Filtre","draft":"Brouillon"},"metadata":{"lang":"fr","fig-responsive":true,"quarto-version":"1.5.57","theme":"cosmo"},"extensions":{"book":{"multiFile":true}}},"pdf":{"identifier":{"display-name":"PDF","target-format":"pdf","base-format":"pdf"},"execute":{"fig-width":5.5,"fig-height":3.5,"fig-format":"pdf","fig-dpi":300,"df-print":"default","error":false,"eval":true,"cache":null,"freeze":false,"echo":true,"output":true,"warning":true,"include":true,"keep-md":false,"keep-ipynb":false,"ipynb":null,"enabled":null,"daemon":null,"daemon-restart":false,"debug":false,"ipynb-filters":[],"ipynb-shell-interactivity":null,"plotly-connected":true,"engine":"markdown"},"render":{"keep-tex":false,"keep-typ":false,"keep-source":false,"keep-hidden":false,"prefer-html":false,"output-divs":true,"output-ext":"pdf","fig-align":"default","fig-pos":null,"fig-env":null,"code-fold":"none","code-overflow":"scroll","code-link":false,"code-line-numbers":false,"code-tools":false,"tbl-colwidths":true,"merge-includes":true,"inline-includes":false,"preserve-yaml":false,"latex-auto-mk":true,"latex-auto-install":true,"latex-clean":true,"latex-min-runs":1,"latex-max-runs":10,"latex-makeindex":"makeindex","latex-makeindex-opts":[],"latex-tlmgr-opts":[],"latex-input-paths":[],"latex-output-dir":null,"link-external-icon":false,"link-external-newwindow":false,"self-contained-math":false,"format-resources":[]},"pandoc":{"pdf-engine":"xelatex","standalone":true,"variables":{"graphics":true,"tables":true},"default-image-extension":"pdf","to":"pdf","output-file":"prepublication.pdf"},"language":{"toc-title-document":"Table des matières","toc-title-website":"Sur cette page","related-formats-title":"Autres formats","related-notebooks-title":"Notebooks","source-notebooks-prefix":"La source","other-links-title":"Autres liens","code-links-title":"Liens de code","launch-dev-container-title":"Lancer le Dev Container","launch-binder-title":"Lancer le Binder","article-notebook-label":"Cahier d'articles","notebook-preview-download":"Télécharger le cahier","notebook-preview-download-src":"Télécharger le code source","notebook-preview-back":"Retour à l'article","manuscript-meca-bundle":"Archive MECA","section-title-abstract":"Résumé","section-title-appendices":"Annexes","section-title-footnotes":"Notes de bas de page","section-title-references":"Les références","section-title-reuse":"Réutilisation","section-title-copyright":"Droits d'auteur","section-title-citation":"Citation","appendix-attribution-cite-as":"Veuillez citer ce travail comme suit :","appendix-attribution-bibtex":"BibTeX","appendix-view-license":"Voir la Licence","title-block-author-single":"Auteur·rice","title-block-author-plural":"Auteur·rice·s","title-block-affiliation-single":"Affiliation","title-block-affiliation-plural":"Affiliations","title-block-published":"Date de publication","title-block-modified":"Modifié","title-block-keywords":"Mots clés","callout-tip-title":"Astuce","callout-note-title":"Note","callout-warning-title":"Avertissement","callout-important-title":"Important","callout-caution-title":"Mise en garde","code-summary":"Code","code-tools-menu-caption":"Code","code-tools-show-all-code":"Montrer tout le code","code-tools-hide-all-code":"Cacher tout le code","code-tools-view-source":"Voir les sources","code-tools-source-code":"Code source","tools-share":"Share","tools-download":"Download","code-line":"Ligne","code-lines":"Lignes","copy-button-tooltip":"Copier vers le presse-papier","copy-button-tooltip-success":"Copié","repo-action-links-edit":"Modifier cette page","repo-action-links-source":"Voir la source","repo-action-links-issue":"Faire part d'un problème","back-to-top":"Retour au sommet","search-no-results-text":"Pas de résultats","search-matching-documents-text":"documents trouvés","search-copy-link-title":"Copier le lien vers la recherche","search-hide-matches-text":"Cacher les correspondances additionnelles","search-more-match-text":"correspondance de plus dans ce document","search-more-matches-text":"correspondances de plus dans ce document","search-clear-button-title":"Effacer","search-text-placeholder":"","search-detached-cancel-button-title":"Annuler","search-submit-button-title":"Envoyer","search-label":"Recherche","toggle-section":"Basculer la section","toggle-sidebar":"Basculer la barre latérale","toggle-dark-mode":"Basculer le mode sombre","toggle-reader-mode":"Basculer en mode lecteur","toggle-navigation":"Basculer la navigation","crossref-fig-title":"Figure","crossref-tbl-title":"Table","crossref-lst-title":"Listing","crossref-thm-title":"Théorème","crossref-lem-title":"Lemme","crossref-cor-title":"Corollaire","crossref-prp-title":"Proposition","crossref-cnj-title":"Conjecture","crossref-def-title":"Définition","crossref-exm-title":"Exemple","crossref-exr-title":"Exercice","crossref-ch-prefix":"Chapitre","crossref-apx-prefix":"Annexe","crossref-sec-prefix":"Section","crossref-eq-prefix":"Équation","crossref-lof-title":"Liste des Figures","crossref-lot-title":"Liste des Tables","crossref-lol-title":"Liste des Listings","environment-proof-title":"Preuve","environment-remark-title":"Remarque","environment-solution-title":"Solution","listing-page-order-by":"Trier par","listing-page-order-by-default":"Ordre par défaut","listing-page-order-by-date-asc":"Le plus ancien","listing-page-order-by-date-desc":"Le plus récent","listing-page-order-by-number-desc":"Descendant","listing-page-order-by-number-asc":"Ascendant","listing-page-field-date":"Date","listing-page-field-title":"Titre","listing-page-field-description":"Description","listing-page-field-author":"Auteur·rice","listing-page-field-filename":"Nom de fichier","listing-page-field-filemodified":"Modifié","listing-page-field-subtitle":"Sous-titre","listing-page-field-readingtime":"Temps de lecture","listing-page-field-wordcount":"Compteur de Mots","listing-page-field-categories":"Catégories","listing-page-minutes-compact":"{0} min.","listing-page-category-all":"Tous","listing-page-no-matches":"Aucun article correspondant","listing-page-words":"{0} mots","listing-page-filter":"Filtre","draft":"Brouillon"},"metadata":{"block-headings":true,"lang":"fr","documentclass":"scrreprt","geometry":["inner=2cm","outer=2cm","top=2cm","bottom=2cm","headsep=22pt","headheight=11pt","footskip=33pt","ignorehead","ignorefoot","heightrounded"]},"extensions":{"book":{"selfContainedOutput":true}}},"epub":{"identifier":{"display-name":"ePub","target-format":"epub","base-format":"epub"},"execute":{"fig-width":5,"fig-height":4,"fig-format":"png","fig-dpi":96,"df-print":"default","error":false,"eval":true,"cache":null,"freeze":false,"echo":true,"output":true,"warning":true,"include":true,"keep-md":false,"keep-ipynb":false,"ipynb":null,"enabled":null,"daemon":null,"daemon-restart":false,"debug":false,"ipynb-filters":[],"ipynb-shell-interactivity":null,"plotly-connected":true,"engine":"markdown"},"render":{"keep-tex":false,"keep-typ":false,"keep-source":false,"keep-hidden":false,"prefer-html":false,"output-divs":true,"output-ext":"epub","fig-align":"default","fig-pos":null,"fig-env":null,"code-fold":"none","code-overflow":"scroll","code-link":false,"code-line-numbers":false,"code-tools":false,"tbl-colwidths":true,"merge-includes":false,"inline-includes":false,"preserve-yaml":false,"latex-auto-mk":true,"latex-auto-install":true,"latex-clean":true,"latex-min-runs":1,"latex-max-runs":10,"latex-makeindex":"makeindex","latex-makeindex-opts":[],"latex-tlmgr-opts":[],"latex-input-paths":[],"latex-output-dir":null,"link-external-icon":false,"link-external-newwindow":false,"self-contained-math":false,"format-resources":[]},"pandoc":{"default-image-extension":"png","html-math-method":"mathml","to":"epub","output-file":"prepublication.epub"},"language":{"toc-title-document":"Table des matières","toc-title-website":"Sur cette page","related-formats-title":"Autres formats","related-notebooks-title":"Notebooks","source-notebooks-prefix":"La source","other-links-title":"Autres liens","code-links-title":"Liens de code","launch-dev-container-title":"Lancer le Dev Container","launch-binder-title":"Lancer le Binder","article-notebook-label":"Cahier d'articles","notebook-preview-download":"Télécharger le cahier","notebook-preview-download-src":"Télécharger le code source","notebook-preview-back":"Retour à l'article","manuscript-meca-bundle":"Archive MECA","section-title-abstract":"Résumé","section-title-appendices":"Annexes","section-title-footnotes":"Notes de bas de page","section-title-references":"Les références","section-title-reuse":"Réutilisation","section-title-copyright":"Droits d'auteur","section-title-citation":"Citation","appendix-attribution-cite-as":"Veuillez citer ce travail comme suit :","appendix-attribution-bibtex":"BibTeX","appendix-view-license":"Voir la Licence","title-block-author-single":"Auteur·rice","title-block-author-plural":"Auteur·rice·s","title-block-affiliation-single":"Affiliation","title-block-affiliation-plural":"Affiliations","title-block-published":"Date de publication","title-block-modified":"Modifié","title-block-keywords":"Mots clés","callout-tip-title":"Astuce","callout-note-title":"Note","callout-warning-title":"Avertissement","callout-important-title":"Important","callout-caution-title":"Mise en garde","code-summary":"Code","code-tools-menu-caption":"Code","code-tools-show-all-code":"Montrer tout le code","code-tools-hide-all-code":"Cacher tout le code","code-tools-view-source":"Voir les sources","code-tools-source-code":"Code source","tools-share":"Share","tools-download":"Download","code-line":"Ligne","code-lines":"Lignes","copy-button-tooltip":"Copier vers le presse-papier","copy-button-tooltip-success":"Copié","repo-action-links-edit":"Modifier cette page","repo-action-links-source":"Voir la source","repo-action-links-issue":"Faire part d'un problème","back-to-top":"Retour au sommet","search-no-results-text":"Pas de résultats","search-matching-documents-text":"documents trouvés","search-copy-link-title":"Copier le lien vers la recherche","search-hide-matches-text":"Cacher les correspondances additionnelles","search-more-match-text":"correspondance de plus dans ce document","search-more-matches-text":"correspondances de plus dans ce document","search-clear-button-title":"Effacer","search-text-placeholder":"","search-detached-cancel-button-title":"Annuler","search-submit-button-title":"Envoyer","search-label":"Recherche","toggle-section":"Basculer la section","toggle-sidebar":"Basculer la barre latérale","toggle-dark-mode":"Basculer le mode sombre","toggle-reader-mode":"Basculer en mode lecteur","toggle-navigation":"Basculer la navigation","crossref-fig-title":"Figure","crossref-tbl-title":"Table","crossref-lst-title":"Listing","crossref-thm-title":"Théorème","crossref-lem-title":"Lemme","crossref-cor-title":"Corollaire","crossref-prp-title":"Proposition","crossref-cnj-title":"Conjecture","crossref-def-title":"Définition","crossref-exm-title":"Exemple","crossref-exr-title":"Exercice","crossref-ch-prefix":"Chapitre","crossref-apx-prefix":"Annexe","crossref-sec-prefix":"Section","crossref-eq-prefix":"Équation","crossref-lof-title":"Liste des Figures","crossref-lot-title":"Liste des Tables","crossref-lol-title":"Liste des Listings","environment-proof-title":"Preuve","environment-remark-title":"Remarque","environment-solution-title":"Solution","listing-page-order-by":"Trier par","listing-page-order-by-default":"Ordre par défaut","listing-page-order-by-date-asc":"Le plus ancien","listing-page-order-by-date-desc":"Le plus récent","listing-page-order-by-number-desc":"Descendant","listing-page-order-by-number-asc":"Ascendant","listing-page-field-date":"Date","listing-page-field-title":"Titre","listing-page-field-description":"Description","listing-page-field-author":"Auteur·rice","listing-page-field-filename":"Nom de fichier","listing-page-field-filemodified":"Modifié","listing-page-field-subtitle":"Sous-titre","listing-page-field-readingtime":"Temps de lecture","listing-page-field-wordcount":"Compteur de Mots","listing-page-field-categories":"Catégories","listing-page-minutes-compact":"{0} min.","listing-page-category-all":"Tous","listing-page-no-matches":"Aucun article correspondant","listing-page-words":"{0} mots","listing-page-filter":"Filtre","draft":"Brouillon"},"metadata":{"lang":"fr"},"extensions":{"book":{"selfContainedOutput":true}}}},"projectFormats":["html","pdf","epub"]}